Topsis/__init__.py
Topsis/topsis_simar.py
Topsis_Simardeep_102003559-1.0.0.dist-info/LICENCE.txt
Topsis_Simardeep_102003559-1.0.0.dist-info/METADATA
Topsis_Simardeep_102003559-1.0.0.dist-info/WHEEL
Topsis_Simardeep_102003559-1.0.0.dist-info/entry_points.txt
Topsis_Simardeep_102003559-1.0.0.dist-info/top_level.txt
Topsis_Simardeep_102003559-1.0.0.dist-info/RECORD
