Metadata-Version: 2.1
Name: Topsis-Simardeep-102003559
Version: 1.0.0
Summary: Topsis package for Multiple Criteria Decision Making problems(MCDM) problems
Home-page: UNKNOWN
Author: Simardeep Singh
Author-email: ssingh22_be20@thapar.edu
License: UNKNOWN
Platform: UNKNOWN
Classifier: Programming Language :: Python :: 3
Classifier: Programming Language :: Python :: 3.6
Classifier: Programming Language :: Python :: 3.7
Classifier: Programming Language :: Python :: 3.8
Classifier: Programming Language :: Python :: 3.9
Classifier: Programming Language :: Python :: 3.10
Classifier: License :: OSI Approved :: MIT License
Classifier: Operating System :: OS Independent
Requires-Python: >=3.6
License-File: LICENCE.txt
